svim/SVCandidate.py
svim/SVIM.py
svim/SVIM_CLUSTER.py
svim/SVIM_COLLECT.py
svim/SVIM_COMBINE.py
svim/SVIM_alignment.py
svim/SVIM_clustering.py
svim/SVIM_fullread.py
svim/SVIM_genotyping.py
svim/SVIM_input_parsing.py
svim/SVIM_inter.py
svim/SVIM_intra.py
svim/SVIM_merging.py
svim/SVIM_plot.py
svim/SVIM_splitread.py
svim/SVSignature.py
svim/__init__.py
svim-2.0.0.data/data/LICENSE
svim-2.0.0.data/scripts/svim
tests/__init__.py
tests/test_Collect.py
tests/test_SVCandidate.py
tests/test_Signature.py
tests/test_clustering.py
tests/test_consensus.py
tests/test_input_parsing.py
tests/test_inter.py
tests/test_intra.py
tests/test_satag.py
svim-2.0.0.dist-info/LICENSE
svim-2.0.0.dist-info/METADATA
svim-2.0.0.dist-info/WHEEL
svim-2.0.0.dist-info/top_level.txt
svim-2.0.0.dist-info/RECORD
