Metadata-Version: 2.1
Name: svim
Version: 2.0.0
Summary: A structural variant caller for long reads.
Home-page: https://github.com/eldariont/svim
Author: David Heller
Author-email: heller_d@molgen.mpg.de
License: GPLv3
Keywords: svim SV PacBio structural variation caller
Platform: UNKNOWN
Classifier: Development Status :: 4 - Beta
Classifier: Environment :: Console
Classifier: Intended Audience :: Science/Research
Classifier: Topic :: Scientific/Engineering :: Bio-Informatics
Classifier: License :: OSI Approved :: GNU General Public License v3 (GPLv3)
Classifier: Programming Language :: Python :: 3.6
Requires-Dist: pysam (>=0.15.2)
Requires-Dist: numpy
Requires-Dist: scipy
Requires-Dist: matplotlib (>=3.3.0)
Requires-Dist: edlib
Requires-Dist: pyspoa (>=0.0.6)
Requires-Dist: py-cpuinfo (>=7.0.0)
